neutrophils_classifier_app/app/__init__.py
neutrophils_classifier_app/app/main.py
neutrophils_classifier_app/app/logic/__init__.py
neutrophils_classifier_app/app/logic/background_calculator.py
neutrophils_classifier_app/app/logic/enhanced_data_loader.py
neutrophils_classifier_app/app/logic/fast_image_loader.py
neutrophils_classifier_app/app/logic/file_io.py
neutrophils_classifier_app/app/logic/frontend_cache_manager.py
neutrophils_classifier_app/app/logic/geometry_calculator.py
neutrophils_classifier_app/app/logic/image_renderer.py
neutrophils_classifier_app/app/logic/secondary_renderers.py
neutrophils_classifier_app/app/logic/streamlined_image_manager.py
neutrophils_classifier_app/app/logic/synchronous_vtk_renderer.py
neutrophils_classifier_app/app/logic/threaded_processes.py
neutrophils_classifier_app/app/logic/ui_state_manager.py
neutrophils_classifier_app/app/logic/threads/__init__.py
neutrophils_classifier_app/app/logic/threads/background_threads.py
neutrophils_classifier_app/app/logic/threads/base_worker.py
neutrophils_classifier_app/app/logic/threads/geometry_utils.py
neutrophils_classifier_app/app/logic/threads/image_processing_threads.py
neutrophils_classifier_app/app/logic/threads/loss_utils.py
neutrophils_classifier_app/app/logic/threads/model_threads.py
neutrophils_classifier_app/app/logic/threads/qdrant_threads.py
neutrophils_classifier_app/app/logic/threads/streamlined_loading_thread.py
neutrophils_classifier_app/app/logic/threads/threshold_update_thread.py
neutrophils_classifier_app/app/logic/threads/utility_threads.py
neutrophils_classifier_app/app/logic/threads/vtk_computation_utils.py
neutrophils_classifier_app/app/ui/__init__.py
neutrophils_classifier_app/app/ui/csv_export_utils.py
neutrophils_classifier_app/app/ui/embedded_features.ui
neutrophils_classifier_app/app/ui/embedded_features_window.py
neutrophils_classifier_app/app/ui/geometric_features.ui
neutrophils_classifier_app/app/ui/geometric_features_window.py
neutrophils_classifier_app-1.0.2.dist-info/licenses/LICENSE
neutrophils_classifier_app-1.0.2.dist-info/METADATA
neutrophils_classifier_app-1.0.2.dist-info/WHEEL
neutrophils_classifier_app-1.0.2.dist-info/entry_points.txt
neutrophils_classifier_app-1.0.2.dist-info/top_level.txt
neutrophils_classifier_app-1.0.2.dist-info/RECORD
